videoflow/__init__.py
videoflow/version.py
videoflow/consumers/__init__.py
videoflow/consumers/basic.py
videoflow/consumers/video.py
videoflow/core/__init__.py
videoflow/core/bottlenecks.py
videoflow/core/constants.py
videoflow/core/engine.py
videoflow/core/flow.py
videoflow/core/graph.py
videoflow/core/node.py
videoflow/core/processor.py
videoflow/core/task.py
videoflow/engines/__init__.py
videoflow/engines/batch.py
videoflow/engines/realtime.py
videoflow/engines/task_functions.py
videoflow/engines/zeromq.py
videoflow/processors/__init__.py
videoflow/processors/aggregators.py
videoflow/processors/basic.py
videoflow/processors/vision/__init__.py
videoflow/processors/vision/annotators.py
videoflow/processors/vision/counters.py
videoflow/processors/vision/detectors.py
videoflow/processors/vision/pose.py
videoflow/processors/vision/segmentation.py
videoflow/processors/vision/trackers.py
videoflow/processors/vision/transformers.py
videoflow/producers/__init__.py
videoflow/producers/basic.py
videoflow/producers/video.py
videoflow/utils/__init__.py
videoflow/utils/downloader.py
videoflow/utils/generic_utils.py
videoflow/utils/graph.py
videoflow/utils/keras.py
videoflow/utils/parsers.py
videoflow/utils/system.py
videoflow/utils/tensorflow.py
videoflow/utils/transforms.py
videoflow-0.2.10.dist-info/LICENSE
videoflow-0.2.10.dist-info/METADATA
videoflow-0.2.10.dist-info/WHEEL
videoflow-0.2.10.dist-info/top_level.txt
videoflow-0.2.10.dist-info/RECORD
