Metadata-Version: 2.1
Name: videoflow
Version: 0.2.10
Summary: Python video stream processing library
Home-page: https://github.com/videoflow/videoflow
Author: Jadiel de Armas
Author-email: jadielam@gmail.com
License: MIT
Platform: UNKNOWN
Classifier: Intended Audience :: Developers
Classifier: Intended Audience :: Education
Classifier: License :: OSI Approved :: MIT License
Classifier: Programming Language :: Python :: 3.6
Classifier: Topic :: Software Development :: Libraries
Classifier: Topic :: Software Development :: Libraries :: Python Modules
Requires-Dist: numpy (>=1.9.1)
Requires-Dist: opencv-python (>=4.0.0)
Requires-Dist: six (>=1.9.0)
Requires-Dist: requests (>=2.22.0)
